pysynth/__init__.py
pysynth/__main__.py
pysynth/catdecat.py
pysynth/ipf.py
pysynth-0.0.4.dist-info/LICENSE.txt
pysynth-0.0.4.dist-info/METADATA
pysynth-0.0.4.dist-info/WHEEL
pysynth-0.0.4.dist-info/top_level.txt
pysynth-0.0.4.dist-info/zip-safe
pysynth-0.0.4.dist-info/RECORD
