Metadata-Version: 2.1
Name: pysynth
Version: 0.0.4
Summary: Dataset synthesis for Python
Home-page: https://github.com/simberaj/pysynth
Author: Jan Šimbera
Author-email: simbera.jan@gmail.com
License: MIT
Keywords: synthesis ipf data python
Platform: UNKNOWN
Classifier: Development Status :: 2 - Pre-Alpha
Classifier: Environment :: Console
Classifier: Intended Audience :: Developers
Classifier: License :: OSI Approved :: MIT License
Classifier: Natural Language :: English
Classifier: Programming Language :: Python
Classifier: Programming Language :: Python :: 3
Requires-Python: >=3.7.0
Requires-Dist: numpy
Requires-Dist: pandas
Requires-Dist: scipy
Requires-Dist: scikit-learn (>=0.22)
